[{"message":"123","time":"1575578697830","user":"vedmak"},{"message":"test","time":"1575578701806","user":"vedmak"},{"message":"2222","time":"1575578714934","user":"test2"},{"message":"123","time":"1575578797431","user":"vedmak555"},{"message":"\ud83d\ude00","time":"1575579149268","user":"vedmak555"},{"message":"\ud83d\ude07","time":"1575579173283","user":"vedmak555"},{"message":"\ud83d\ude03","time":"1575579187764","user":"vedmak555"},{"message":"\u263a\u263b","time":"1575579195933","user":"vedmak555"},{"message":"1","time":"1575579931897","user":"vedmak555"},{"message":"2","time":"1575581178174","user":"vedmak"},{"message":"2","time":"1575581184525","user":"vedmak"},{"message":"123","time":"1575581199812","user":"vedmak"},{"message":"123","time":"1575581246286","user":"vedmak"},{"message":"dasdas:)","time":"1575581883578","user":"vedmak"},{"message":"nk:(","time":"1575581932712","user":"vedmak"},{"message":"sadasdd :)","time":"1575582062849","user":"vedmak"},{"message":"d","time":"1576083692253","user":"test"},{"message":"tryrty","time":"1576473305236","user":"vedmak"},{"message":"hello","time":1576473499851,"user":"vedmak"},{"message":"42","time":1576473562905,"user":"<h1>nnn<\/h1>"},{"message":")","time":1576473789055,"user":"test"},{"message":":)","time":1576473793973,"user":"test"},{"message":"asdas :)","time":1576473822900,"user":"test"},{"message":"sdf","time":1576473825502,"user":"test"},{"message":"sda","time":1576473827077,"user":"test"},{"message":"afsaf:)","time":1576473833637,"user":"test"},{"message":"asda","time":1576473834365,"user":"test"},{"message":"dfsdf","time":1576474539212,"user":"test"},{"message":"fsdfsd","time":1576474543018,"user":"test"},{"message":"fd","time":1576475732236,"user":"test"},{"message":"vb","time":1576475747738,"user":"test"},{"message":"dgsdgd","time":1576475752489,"user":"test"},{"message":"kjn","time":1576475766033,"user":"test"},{"message":"zxc","time":1576475865827,"user":"test"},{"message":"sfdfs","time":1576475880955,"user":"test"},{"message":"dfg","time":1576475884456,"user":"test"},{"message":"fasf","time":1576475922219,"user":"test"},{"message":"xcv","time":1576475925105,"user":"test"},{"message":"cxcvxc","time":1576475928599,"user":"test"},{"message":"xcvxcv","time":1576475929342,"user":"test"},{"message":"cvx","time":1576475929838,"user":"test"},{"message":"xc","time":1576475930086,"user":"test"},{"message":"vxc","time":1576475930390,"user":"test"},{"message":"vx","time":1576475930630,"user":"test"},{"message":"sdf","time":1576475950034,"user":"test"},{"message":"dfgdf","time":1576475954128,"user":"test"},{"message":"jmpo","time":1576476011895,"user":"test"},{"message":"123","time":1576620985883,"user":"test"},{"message":"213123","time":1576620995057,"user":"test121"},{"message":"sadsd:)","time":1576621001838,"user":"test121"},{"message":"12312","time":1576621291206,"user":"test22"},{"message":"asd","time":1576621305462,"user":"tes132"},{"message":"sdfsdf","time":1576621319942,"user":"sfddfsdfsd"},{"message":"asd","time":1578947856281,"user":"test"},{"message":"sad","time":1578947857289,"user":"test"},{"message":"asd","time":1578947858457,"user":"test"},{"message":"1","time":1578948202040,"user":"test"},{"message":"1","time":1578948203334,"user":"test"},{"message":"1","time":1578948204647,"user":"test"},{"message":"1","time":1578948316215,"user":"test"},{"message":"1","time":1578948317709,"user":"test"},{"message":"1","time":1578948318933,"user":"test"},{"message":"2","time":1578948407039,"user":"test"},{"message":"2","time":1578948408197,"user":"test"},{"message":"3","time":1578948462046,"user":"test"},{"message":"3","time":1578948465941,"user":"test"},{"message":"3","time":1578948589958,"user":"test"},{"message":"2","time":1578948591252,"user":"test"},{"message":"2","time":1578948593491,"user":"test"},{"message":"3","time":1578948625412,"user":"test"},{"message":"3","time":1578948678493,"user":"test"},{"message":"3","time":1578948679818,"user":"test"},{"message":"2","time":1578948732044,"user":"test"},{"message":"2","time":1578948734114,"user":"test"},{"message":"1","time":1578948766357,"user":"test"},{"message":"1","time":1578948767522,"user":"test"},{"message":"1","time":1578948768818,"user":"test"},{"message":"123123","time":1578948770714,"user":"test"},{"message":"2","time":1578948851346,"user":"test"},{"message":"dqa","time":1578949782716,"user":"test"},{"message":"w","time":1578949788036,"user":"test"},{"message":"sfe","time":1578949789747,"user":"test"},{"message":"esf","time":1578949791915,"user":"test"},{"message":"213","time":1578950201000,"user":"test"},{"message":"2","time":1578950246858,"user":"test"},{"message":"asd","time":1578950259504,"user":"test"},{"message":"213","time":1578950303663,"user":"test"},{"message":"213","time":1578950322860,"user":"test"},{"message":"123","time":1578950324843,"user":"test"},{"message":"21","time":1578950326382,"user":"test"},{"message":"asd","time":1578950339322,"user":"test"},{"message":"asd","time":1578950342842,"user":"test"},{"message":"1","time":1578950650647,"user":"test"},{"message":"213","time":1578950652405,"user":"test"},{"message":"1","time":1578950655861,"user":"test"},{"message":"jh","time":1578950817278,"user":"test"},{"message":"j","time":1578950820436,"user":"test"},{"message":"57","time":1578950855875,"user":"test"},{"message":"uy","time":1578950860395,"user":"test"},{"message":"gh","time":1578950866927,"user":"test"},{"message":"k","time":1578951029268,"user":"test"},{"message":"i","time":1578951069981,"user":"test"},{"message":"4","time":1578957161106,"user":"test"},{"message":"6456","time":1578957163647,"user":"test"},{"message":"45654","time":1578957165583,"user":"test"},{"message":"21312","time":1578957277192,"user":"test"},{"message":"2","time":1578957278279,"user":"test"},{"message":"2","time":1578957280285,"user":"test"},{"message":"2","time":1578957280893,"user":"test"},{"message":"2","time":1578957281365,"user":"test"},{"message":"2","time":1578957281749,"user":"test"},{"message":"2","time":1578957282061,"user":"test"},{"message":"2","time":1578957282317,"user":"test"},{"message":"2","time":1578957282541,"user":"test"},{"message":"2","time":1578957282733,"user":"test"},{"message":"das","time":1578957307711,"user":"test"},{"message":"kj","time":1578957326456,"user":"test"},{"message":"kjl","time":1578957327877,"user":"test"},{"message":"kjl","time":1578957331805,"user":"test"},{"message":"kjljkl","time":1578957333333,"user":"test"},{"message":"kjljk","time":1578957334853,"user":"test"},{"message":"kjljk","time":1578957336149,"user":"test"},{"message":"kjljkl","time":1578957337046,"user":"test"},{"message":"jklkj","time":1578957337694,"user":"test"},{"message":"lkj","time":1578957338093,"user":"test"},{"message":"l","time":1578957338477,"user":"test"},{"message":"jkl","time":1578957338781,"user":"test"},{"message":"jk","time":1578957338973,"user":"test"},{"message":"l","time":1578957339365,"user":"test"},{"message":"jkl","time":1578957339717,"user":"test"},{"message":"jk","time":1578957339949,"user":"test"},{"message":"l","time":1578957340165,"user":"test"},{"message":"kj","time":1578957341181,"user":"test"},{"message":"ljklj","time":1578957342741,"user":"test"},{"message":"jkljkl","time":1578957346645,"user":"test"},{"message":"jkljkl","time":1578957349717,"user":"test"},{"message":"jkljk","time":1578957352173,"user":"test"},{"message":"53","time":1578957389288,"user":"test"},{"message":"ytu","time":1578957391932,"user":"test"},{"message":"ugyi","time":1578957441756,"user":"test"},{"message":"yuiyu","time":1578957443467,"user":"test"},{"message":"uyi","time":1578957448212,"user":"test"},{"message":"uyiyu","time":1578957453332,"user":"test"},{"message":"iyu","time":1578957456532,"user":"test"},{"message":"iyu","time":1578957458524,"user":"test"},{"message":"hg","time":1578957483630,"user":"test"},{"message":"hg","time":1578957486068,"user":"test"},{"message":"hg","time":1578957488108,"user":"test"},{"message":"hg","time":1578957490475,"user":"test"},{"message":"hg","time":1578957493883,"user":"test"},{"message":"sdf","time":1578957643910,"user":"test"},{"message":"fsd","time":1578957645419,"user":"test"},{"message":"sfd","time":1578957651315,"user":"test"},{"message":"sfd","time":1578957652491,"user":"test"},{"message":"sfd","time":1578957659155,"user":"test"},{"message":"sfd","time":1578957660580,"user":"test"},{"message":"sdf","time":1578957661834,"user":"test"},{"message":"sdf","time":1578957662563,"user":"test"},{"message":"sdf","time":1578957663371,"user":"test"},{"message":"dfs","time":1578957663971,"user":"test"},{"message":"dsf","time":1578957664658,"user":"test"},{"message":"sdf","time":1578957665346,"user":"test"},{"message":"sfd","time":1578957667354,"user":"test"},{"message":"1","time":1578957815957,"user":"test"},{"message":"2","time":1578957819115,"user":"test"},{"message":"1","time":1578957823506,"user":"test"},{"message":"2","time":1578957831395,"user":"test"},{"message":"2","time":1578957848722,"user":"test"},{"message":"213123","time":1579377579776,"user":"test"},{"message":"213123","time":1579377580615,"user":"test"},{"message":"21312","time":1579377581447,"user":"test"},{"message":"4","time":1579377581666,"user":"test"},{"message":"4","time":1579377581872,"user":"test"},{"message":"12","time":1579377582056,"user":"test"},{"message":"4","time":1579377582247,"user":"test"},{"message":"12","time":1579377582447,"user":"test"},{"message":"12","time":1579377582625,"user":"test"},{"message":"4","time":1579377582799,"user":"test"},{"message":"12","time":1579377583133,"user":"test"},{"message":"124","time":1579377583167,"user":"test"},{"message":"12412","time":1579377583375,"user":"test"},{"message":"12","time":1579377583695,"user":"test"},{"message":"12","time":1579377584263,"user":"test"},{"message":"214","time":1579377585736,"user":"test"},{"message":"214","time":1579377586455,"user":"test"},{"message":"214","time":1579377587055,"user":"test"},{"message":"12412","time":1579377587727,"user":"test"},{"message":"4124","time":1579377588191,"user":"test"},{"message":"12","time":1579377588471,"user":"test"},{"message":"421","time":1579377588743,"user":"test"},{"message":"421","time":1579377589047,"user":"test"},{"message":"421","time":1579377589431,"user":"test"},{"message":"4213","time":1579377589956,"user":"test"},{"message":"123","time":1579377590479,"user":"test"},{"message":"12312","time":1579377590943,"user":"test"},{"message":"3412","time":1579377591343,"user":"test"},{"message":"312","time":1579377591680,"user":"test"},{"message":"3","time":1579377593767,"user":"test"},{"message":"asfasfasf","time":1579377783737,"user":"test"},{"message":"saf","time":1579377925120,"user":"test"},{"message":"213","time":1579378042200,"user":"test"},{"message":"123","time":1579378043237,"user":"test"},{"message":"1312","time":1579378079903,"user":"test"},{"message":"412","time":1579378080860,"user":"test"},{"message":"214","time":1579378081532,"user":"test"},{"message":"124","time":1579378081994,"user":"test"},{"message":"123","time":1579378085484,"user":"test"}]